{
  "version": "4.4.15",
  "downloadUrl": "https://github.com/vsisnet/VsisLogin-Release/releases/download/v4.4.15/VsisLogin_v4.4.15.zip",
  "downloadZipUrl": "https://github.com/vsisnet/VsisLogin-Release/releases/download/v4.4.15/VsisLogin_v4.4.15.zip",
  "releasedAt": "2026-05-16",
  "notes": "v4.4.15 — Verify v4.4.14 updater family stage-aside\n\nKhông có code change. Verify v4.4.14 IsRunningUpdaterFile prefix match + App.OnStartup PromotePendingUpdaterBinary scan *.new global.\n\nLưu ý chicken-and-egg: user v4.4.13 KHÔNG self-update được lên v4.4.15 vì fix nằm trong updater binary v4.4.14+, còn updater v4.4.13 đang chạy không biết stage-aside .dll. Cần manual download v4.4.14 hoặc v4.4.15 1 lần để lấy updater binary mới trên disk. Từ v4.4.14 trở đi in-place update work end-to-end auto-relaunch."
}
